pyopenbt/__init__.py
pyopenbt/openbt.py
pyopenbt-0.0.8.dist-info/LICENSE
pyopenbt-0.0.8.dist-info/METADATA
pyopenbt-0.0.8.dist-info/WHEEL
pyopenbt-0.0.8.dist-info/top_level.txt
pyopenbt-0.0.8.dist-info/RECORD
