Metadata-Version: 2.1
Name: pyopenbt
Version: 0.0.8
Summary: python interface to openbt
Author-email: Clark Van Lieshout <clarkvan33@gmail.com>, "J. Derek Tucker" <jdtuck@sandia.gov>
License: BSD 3-Clause
Project-URL: homepage, https://github.com/cavan33/openbt_py
Project-URL: repository, https://github.com/cavan33/openbt_py
Keywords: bayesian additive regession trees
Classifier: License :: OSI Approved :: BSD License
Classifier: Operating System :: OS Independent
Classifier: Programming Language :: Python
Classifier: Topic :: Scientific/Engineering
Classifier: Topic :: Scientific/Engineering :: Mathematics
Classifier: Programming Language :: Python :: 3
Classifier: Programming Language :: Python :: 3.6
Requires-Python: >=3.6
License-File: LICENSE
Requires-Dist: numpy
Requires-Dist: scipy
Requires-Dist: pandas
Requires-Dist: scikit-learn
Requires-Dist: matplotlib
Requires-Dist: joblib
